Workbook

Sheet Summary
A1: Factory loan schedule - test cases (FactorySchedule.vb, Panha)
A2: Each sheet is one case generated by the real FactorySchedule.BuildSchedule module, with BK_Holiday rows from the local Panha database (plus simulated holidays where the case says so). Paydays are hard-coded to the 10th and 25th; first payday must be at least 5 days after disbursement.
A4: Case | B4: What it proves | C4: Disbursed | D4: Amount | E4: Rate %/month | F4: Term | G4: Type | H4: Currency | I4: First due | J4: Maturity | K4: Total interest (_Amt)
A5: 1 Flat worked example | B5: Customer's example: 1,000,000 KHR, 2%/month, 6 installments, disbursed 3 Nov 2025. Row 1 pro-rated 7 days; rows 2-6 fixed 10,000. 10 Jan and 25 Jan 2026 fall on a weekend and move to the Monday. | C5: 2025-11-03 | D5: 1000000 | E5: 2 | F5: 6 | G5: ថេរ (flat) | H5: រៀល (KHR) | I5: 2025-11-10 | J5: 2026-01-26 | K5: ='1 Flat worked example'!K23
A6: 2 Declining worked example | B6: Same loan as case 1 but declining type: interest = previous outstanding balance x 1% (half of 2%). | C6: 2025-11-03 | D6: 1000000 | E6: 2 | F6: 6 | G6: ចុះ (declining) | H6: រៀល (KHR) | I6: 2025-11-10 | J6: 2026-01-26 | K6: ='2 Declining worked example'!K23
A7: 3 Skip payday under 5 days | B7: Disbursed 6 Nov 2025: the 10th is only 4 days away, so the first installment skips to 25 Nov (19 days of interest). | C7: 2025-11-06 | D7: 1000000 | E7: 2 | F7: 4 | G7: ថេរ (flat) | H7: រៀល (KHR) | I7: 2025-11-25 | J7: 2026-01-12 | K7: ='3 Skip payday under 5 days'!K21
A8: 4 Exactly 5 days is allowed | B8: Disbursed 5 Nov 2025: the 10th is 5 days away, which is the minimum, so it is kept (5 days of interest). | C8: 2025-11-05 | D8: 1000000 | E8: 2 | F8: 4 | G8: ថេរ (flat) | H8: រៀល (KHR) | I8: 2025-11-10 | J8: 2025-12-25 | K8: ='4 Exactly 5 days is allowed'!K21
A9: 5 Disbursed on a payday | B9: Disbursed on 25 Nov 2025 itself: the next payday is 10 Dec (15 days), nothing is skipped. | C9: 2025-11-25 | D9: 2000000 | E9: 3 | F9: 4 | G9: ថេរ (flat) | H9: រៀល (KHR) | I9: 2025-12-10 | J9: 2026-01-26 | K9: ='5 Disbursed on a payday'!K21
A10: 6 Single holiday - collect before | B10: Simulated holiday on Thu 25 Dec 2025 (1 closed day, no weekend touching it): collected on Wed 24 Dec. Interest unchanged. | C10: 2025-11-03 | D10: 1000000 | E10: 2 | F10: 4 | G10: ថេរ (flat) | H10: រៀល (KHR) | I10: 2025-11-10 | J10: 2025-12-24 | K10: ='6 Single holiday (before)'!K21
A11: 7 Holiday + weekend - collect after | B11: Simulated holiday on Fri 10 Apr 2026 joined to the weekend (3 closed days): collected on Mon 13 Apr. Also 10 Jan / 25 Jan 2026 weekends. | C11: 2025-12-01 | D11: 1000000 | E11: 2 | F11: 10 | G11: ថេរ (flat) | H11: រៀល (KHR) | I11: 2025-12-10 | J11: 2026-04-27 | K11: ='7 Holiday + weekend (after)'!K27
A12: 8 Two holidays in a row - after | B12: Simulated holidays Tue 25 Nov and Wed 26 Nov 2025 (2 closed days): collected Thu 27 Nov. | C12: 2025-11-03 | D12: 1000000 | E12: 2 | F12: 3 | G12: ថេរ (flat) | H12: រៀល (KHR) | I12: 2025-11-10 | J12: 2025-12-10 | K12: ='8 Two holidays in a row (after)'!K20
A13: 9 USD loan - no rounding | B13: USD 500 at 2.5%/month, 4 installments, declining: amounts are stored as computed, no rounding to 100. | C13: 2025-11-12 | D13: 500 | E13: 2.5 | F13: 4 | G13: ចុះ (declining) | H13: ដុល្លារ (USD) | I13: 2025-11-25 | J13: 2026-01-12 | K13: ='9 USD loan (no rounding)'!K21
A14: 10 Principal remainder | B14: 1,000,000 KHR over 7 installments: 142,857.14 x 6 and the last one 142,857.16 so the balance ends at exactly 0. | C14: 2025-11-03 | D14: 1000000 | E14: 2 | F14: 7 | G14: ថេរ (flat) | H14: រៀល (KHR) | I14: 2025-11-10 | J14: 2026-02-10 | K14: ='10 Principal remainder'!K24
A15: 11 Year end rollover | B15: Disbursed 20 Dec 2025: 25 Dec kept (5 days), then 10 Jan 2026 (Sat -> Mon 12), 25 Jan (Sun -> Mon 26). DB holiday 29 Dec is not a payday so it has no effect. | C15: 2025-12-20 | D15: 3000000 | E15: 2 | F15: 4 | G15: ចុះ (declining) | H15: រៀល (KHR) | I15: 2025-12-25 | J15: 2026-02-10 | K15: ='11 Year end rollover'!K21

Sheet 1 Flat worked example
A1: 1 Flat worked example
A2: Customer's example: 1,000,000 KHR, 2%/month, 6 installments, disbursed 3 Nov 2025. Row 1 pro-rated 7 days; rows 2-6 fixed 10,000. 10 Jan and 25 Jan 2026 fall on a weekend and move to the Monday.
A4: Disbursement date (LD_Dis_Date) | B4: 2025-11-03
A5: Amount (LD_Dis_Amt) | B5: 1000000
A6: Rate per month % (LD_IntRate) | B6: 2
A7: Term = installments (LD_Term) | B7: 6
A8: Type (LD_Type) | B8: ថេរ (flat)
A9: Currency | B9: រៀល (KHR)
A10: Unit (LD_Unit) | B10: រោងចក្រ (factory, code 5)
A11: First payment (LD_First_Date) | B11: 2025-11-10
A12: Maturity (LD_Mat_Date) | B12: 2026-01-26
A13: Holidays in range | B13: 2025-11-04 (BK_Holiday), 2025-11-05 (BK_Holiday), 2025-11-06 (BK_Holiday), 2025-11-09 (BK_Holiday), 2025-12-29 (BK_Holiday)
A14: Interest rule: row 1 = Amount x Rate% / 30 x Days; rows 2+ = basis x Rate% / 2 (basis = Amount for flat, previous SH_Balance_Org for declining). KHR amounts in the _Amt columns are rounded up to the next 100 by ReturnRound; _Org keeps the exact value.
A16: No | B16: Payday (10th/25th) | C16: SH_Date (due date) | D16: Weekday | E16: Shifted? | F16: Days of interest | G16: SH_Prn_Org | H16: SH_Int_Org | I16: SH_Balance_Org | J16: SH_Prn_Amt | K16: SH_Int_Amt | L16: SH_Balance | M16: Total to pay (Prn+Int)
A17: 1 | B17: 2025-11-10 | C17: 2025-11-10 | D17: Monday | F17: 7 | G17: 166666.67 | H17: 4666.6667 | I17: 833333.33 | J17: 166700 | K17: 4700 | L17: 833400 | M17: =J17+K17
A18: 2 | B18: 2025-11-25 | C18: 2025-11-25 | D18: Tuesday | F18: 15 | G18: 166666.67 | H18: 10000 | I18: 666666.66 | J18: 166700 | K18: 10000 | L18: 666700 | M18: =J18+K18
A19: 3 | B19: 2025-12-10 | C19: 2025-12-10 | D19: Wednesday | F19: 15 | G19: 166666.67 | H19: 10000 | I19: 499999.99 | J19: 166700 | K19: 10000 | L19: 500000 | M19: =J19+K19
A20: 4 | B20: 2025-12-25 | C20: 2025-12-25 | D20: Thursday | F20: 15 | G20: 166666.67 | H20: 10000 | I20: 333333.32 | J20: 166700 | K20: 10000 | L20: 333400 | M20: =J20+K20
A21: 5 | B21: 2026-01-10 | C21: 2026-01-12 | D21: Monday | E21: yes | F21: 16 | G21: 166666.67 | H21: 10000 | I21: 166666.65 | J21: 166700 | K21: 10000 | L21: 166700 | M21: =J21+K21
A22: 6 | B22: 2026-01-25 | C22: 2026-01-26 | D22: Monday | E22: yes | F22: 15 | G22: 166666.65 | H22: 10000 | I22: 0 | J22: 166700 | K22: 10000 | L22: 0 | M22: =J22+K22
A23: Total | G23: =SUM(G17:G22) | H23: =SUM(H17:H22) | J23: =SUM(J17:J22) | K23: =SUM(K17:K22) | M23: =SUM(M17:M22)
A24: Check: principal total equals amount | G24: =IF(ROUND(G23-B5,2)=0,"OK","DIFF")
A25: Legend: yellow = due date moved off a weekend/holiday; green = first installment pro-rated by days.

Sheet 2 Declining worked example
A1: 2 Declining worked example
A2: Same loan as case 1 but declining type: interest = previous outstanding balance x 1% (half of 2%).
A4: Disbursement date (LD_Dis_Date) | B4: 2025-11-03
A5: Amount (LD_Dis_Amt) | B5: 1000000
A6: Rate per month % (LD_IntRate) | B6: 2
A7: Term = installments (LD_Term) | B7: 6
A8: Type (LD_Type) | B8: ចុះ (declining)
A9: Currency | B9: រៀល (KHR)
A10: Unit (LD_Unit) | B10: រោងចក្រ (factory, code 5)
A11: First payment (LD_First_Date) | B11: 2025-11-10
A12: Maturity (LD_Mat_Date) | B12: 2026-01-26
A13: Holidays in range | B13: 2025-11-04 (BK_Holiday), 2025-11-05 (BK_Holiday), 2025-11-06 (BK_Holiday), 2025-11-09 (BK_Holiday), 2025-12-29 (BK_Holiday)
A14: Interest rule: row 1 = Amount x Rate% / 30 x Days; rows 2+ = basis x Rate% / 2 (basis = Amount for flat, previous SH_Balance_Org for declining). KHR amounts in the _Amt columns are rounded up to the next 100 by ReturnRound; _Org keeps the exact value.
A16: No | B16: Payday (10th/25th) | C16: SH_Date (due date) | D16: Weekday | E16: Shifted? | F16: Days of interest | G16: SH_Prn_Org | H16: SH_Int_Org | I16: SH_Balance_Org | J16: SH_Prn_Amt | K16: SH_Int_Amt | L16: SH_Balance | M16: Total to pay (Prn+Int)
A17: 1 | B17: 2025-11-10 | C17: 2025-11-10 | D17: Monday | F17: 7 | G17: 166666.67 | H17: 4666.6667 | I17: 833333.33 | J17: 166700 | K17: 4700 | L17: 833400 | M17: =J17+K17
A18: 2 | B18: 2025-11-25 | C18: 2025-11-25 | D18: Tuesday | F18: 15 | G18: 166666.67 | H18: 8333.3333 | I18: 666666.66 | J18: 166700 | K18: 8400 | L18: 666700 | M18: =J18+K18
A19: 3 | B19: 2025-12-10 | C19: 2025-12-10 | D19: Wednesday | F19: 15 | G19: 166666.67 | H19: 6666.6666 | I19: 499999.99 | J19: 166700 | K19: 6700 | L19: 500000 | M19: =J19+K19
A20: 4 | B20: 2025-12-25 | C20: 2025-12-25 | D20: Thursday | F20: 15 | G20: 166666.67 | H20: 4999.9999 | I20: 333333.32 | J20: 166700 | K20: 5000 | L20: 333400 | M20: =J20+K20
A21: 5 | B21: 2026-01-10 | C21: 2026-01-12 | D21: Monday | E21: yes | F21: 16 | G21: 166666.67 | H21: 3333.3332 | I21: 166666.65 | J21: 166700 | K21: 3400 | L21: 166700 | M21: =J21+K21
A22: 6 | B22: 2026-01-25 | C22: 2026-01-26 | D22: Monday | E22: yes | F22: 15 | G22: 166666.65 | H22: 1666.6665 | I22: 0 | J22: 166700 | K22: 1700 | L22: 0 | M22: =J22+K22
A23: Total | G23: =SUM(G17:G22) | H23: =SUM(H17:H22) | J23: =SUM(J17:J22) | K23: =SUM(K17:K22) | M23: =SUM(M17:M22)
A24: Check: principal total equals amount | G24: =IF(ROUND(G23-B5,2)=0,"OK","DIFF")
A25: Legend: yellow = due date moved off a weekend/holiday; green = first installment pro-rated by days.

Sheet 3 Skip payday under 5 days
A1: 3 Skip payday under 5 days
A2: Disbursed 6 Nov 2025: the 10th is only 4 days away, so the first installment skips to 25 Nov (19 days of interest).
A4: Disbursement date (LD_Dis_Date) | B4: 2025-11-06
A5: Amount (LD_Dis_Amt) | B5: 1000000
A6: Rate per month % (LD_IntRate) | B6: 2
A7: Term = installments (LD_Term) | B7: 4
A8: Type (LD_Type) | B8: ថេរ (flat)
A9: Currency | B9: រៀល (KHR)
A10: Unit (LD_Unit) | B10: រោងចក្រ (factory, code 5)
A11: First payment (LD_First_Date) | B11: 2025-11-25
A12: Maturity (LD_Mat_Date) | B12: 2026-01-12
A13: Holidays in range | B13: 2025-11-06 (BK_Holiday), 2025-11-09 (BK_Holiday), 2025-12-29 (BK_Holiday)
A14: Interest rule: row 1 = Amount x Rate% / 30 x Days; rows 2+ = basis x Rate% / 2 (basis = Amount for flat, previous SH_Balance_Org for declining). KHR amounts in the _Amt columns are rounded up to the next 100 by ReturnRound; _Org keeps the exact value.
A16: No | B16: Payday (10th/25th) | C16: SH_Date (due date) | D16: Weekday | E16: Shifted? | F16: Days of interest | G16: SH_Prn_Org | H16: SH_Int_Org | I16: SH_Balance_Org | J16: SH_Prn_Amt | K16: SH_Int_Amt | L16: SH_Balance | M16: Total to pay (Prn+Int)
A17: 1 | B17: 2025-11-25 | C17: 2025-11-25 | D17: Tuesday | F17: 19 | G17: 250000 | H17: 12666.667 | I17: 750000 | J17: 250000 | K17: 12700 | L17: 750000 | M17: =J17+K17
A18: 2 | B18: 2025-12-10 | C18: 2025-12-10 | D18: Wednesday | F18: 15 | G18: 250000 | H18: 10000 | I18: 500000 | J18: 250000 | K18: 10000 | L18: 500000 | M18: =J18+K18
A19: 3 | B19: 2025-12-25 | C19: 2025-12-25 | D19: Thursday | F19: 15 | G19: 250000 | H19: 10000 | I19: 250000 | J19: 250000 | K19: 10000 | L19: 250000 | M19: =J19+K19
A20: 4 | B20: 2026-01-10 | C20: 2026-01-12 | D20: Monday | E20: yes | F20: 16 | G20: 250000 | H20: 10000 | I20: 0 | J20: 250000 | K20: 10000 | L20: 0 | M20: =J20+K20
A21: Total | G21: =SUM(G17:G20) | H21: =SUM(H17:H20) | J21: =SUM(J17:J20) | K21: =SUM(K17:K20) | M21: =SUM(M17:M20)
A22: Check: principal total equals amount | G22: =IF(ROUND(G21-B5,2)=0,"OK","DIFF")
A23: Legend: yellow = due date moved off a weekend/holiday; green = first installment pro-rated by days.

Sheet 4 Exactly 5 days is allowed
A1: 4 Exactly 5 days is allowed
A2: Disbursed 5 Nov 2025: the 10th is 5 days away, which is the minimum, so it is kept (5 days of interest).
A4: Disbursement date (LD_Dis_Date) | B4: 2025-11-05
A5: Amount (LD_Dis_Amt) | B5: 1000000
A6: Rate per month % (LD_IntRate) | B6: 2
A7: Term = installments (LD_Term) | B7: 4
A8: Type (LD_Type) | B8: ថេរ (flat)
A9: Currency | B9: រៀល (KHR)
A10: Unit (LD_Unit) | B10: រោងចក្រ (factory, code 5)
A11: First payment (LD_First_Date) | B11: 2025-11-10
A12: Maturity (LD_Mat_Date) | B12: 2025-12-25
A13: Holidays in range | B13: 2025-11-05 (BK_Holiday), 2025-11-06 (BK_Holiday), 2025-11-09 (BK_Holiday)
A14: Interest rule: row 1 = Amount x Rate% / 30 x Days; rows 2+ = basis x Rate% / 2 (basis = Amount for flat, previous SH_Balance_Org for declining). KHR amounts in the _Amt columns are rounded up to the next 100 by ReturnRound; _Org keeps the exact value.
A16: No | B16: Payday (10th/25th) | C16: SH_Date (due date) | D16: Weekday | E16: Shifted? | F16: Days of interest | G16: SH_Prn_Org | H16: SH_Int_Org | I16: SH_Balance_Org | J16: SH_Prn_Amt | K16: SH_Int_Amt | L16: SH_Balance | M16: Total to pay (Prn+Int)
A17: 1 | B17: 2025-11-10 | C17: 2025-11-10 | D17: Monday | F17: 5 | G17: 250000 | H17: 3333.3333 | I17: 750000 | J17: 250000 | K17: 3400 | L17: 750000 | M17: =J17+K17
A18: 2 | B18: 2025-11-25 | C18: 2025-11-25 | D18: Tuesday | F18: 15 | G18: 250000 | H18: 10000 | I18: 500000 | J18: 250000 | K18: 10000 | L18: 500000 | M18: =J18+K18
A19: 3 | B19: 2025-12-10 | C19: 2025-12-10 | D19: Wednesday | F19: 15 | G19: 250000 | H19: 10000 | I19: 250000 | J19: 250000 | K19: 10000 | L19: 250000 | M19: =J19+K19
A20: 4 | B20: 2025-12-25 | C20: 2025-12-25 | D20: Thursday | F20: 15 | G20: 250000 | H20: 10000 | I20: 0 | J20: 250000 | K20: 10000 | L20: 0 | M20: =J20+K20
A21: Total | G21: =SUM(G17:G20) | H21: =SUM(H17:H20) | J21: =SUM(J17:J20) | K21: =SUM(K17:K20) | M21: =SUM(M17:M20)
A22: Check: principal total equals amount | G22: =IF(ROUND(G21-B5,2)=0,"OK","DIFF")
A23: Legend: yellow = due date moved off a weekend/holiday; green = first installment pro-rated by days.

Sheet 5 Disbursed on a payday
A1: 5 Disbursed on a payday
A2: Disbursed on 25 Nov 2025 itself: the next payday is 10 Dec (15 days), nothing is skipped.
A4: Disbursement date (LD_Dis_Date) | B4: 2025-11-25
A5: Amount (LD_Dis_Amt) | B5: 2000000
A6: Rate per month % (LD_IntRate) | B6: 3
A7: Term = installments (LD_Term) | B7: 4
A8: Type (LD_Type) | B8: ថេរ (flat)
A9: Currency | B9: រៀល (KHR)
A10: Unit (LD_Unit) | B10: រោងចក្រ (factory, code 5)
A11: First payment (LD_First_Date) | B11: 2025-12-10
A12: Maturity (LD_Mat_Date) | B12: 2026-01-26
A13: Holidays in range | B13: 2025-12-29 (BK_Holiday)
A14: Interest rule: row 1 = Amount x Rate% / 30 x Days; rows 2+ = basis x Rate% / 2 (basis = Amount for flat, previous SH_Balance_Org for declining). KHR amounts in the _Amt columns are rounded up to the next 100 by ReturnRound; _Org keeps the exact value.
A16: No | B16: Payday (10th/25th) | C16: SH_Date (due date) | D16: Weekday | E16: Shifted? | F16: Days of interest | G16: SH_Prn_Org | H16: SH_Int_Org | I16: SH_Balance_Org | J16: SH_Prn_Amt | K16: SH_Int_Amt | L16: SH_Balance | M16: Total to pay (Prn+Int)
A17: 1 | B17: 2025-12-10 | C17: 2025-12-10 | D17: Wednesday | F17: 15 | G17: 500000 | H17: 30000 | I17: 1500000 | J17: 500000 | K17: 30000 | L17: 1500000 | M17: =J17+K17
A18: 2 | B18: 2025-12-25 | C18: 2025-12-25 | D18: Thursday | F18: 15 | G18: 500000 | H18: 30000 | I18: 1000000 | J18: 500000 | K18: 30000 | L18: 1000000 | M18: =J18+K18
A19: 3 | B19: 2026-01-10 | C19: 2026-01-12 | D19: Monday | E19: yes | F19: 16 | G19: 500000 | H19: 30000 | I19: 500000 | J19: 500000 | K19: 30000 | L19: 500000 | M19: =J19+K19
A20: 4 | B20: 2026-01-25 | C20: 2026-01-26 | D20: Monday | E20: yes | F20: 15 | G20: 500000 | H20: 30000 | I20: 0 | J20: 500000 | K20: 30000 | L20: 0 | M20: =J20+K20
A21: Total | G21: =SUM(G17:G20) | H21: =SUM(H17:H20) | J21: =SUM(J17:J20) | K21: =SUM(K17:K20) | M21: =SUM(M17:M20)
A22: Check: principal total equals amount | G22: =IF(ROUND(G21-B5,2)=0,"OK","DIFF")
A23: Legend: yellow = due date moved off a weekend/holiday; green = first installment pro-rated by days.

Sheet 6 Single holiday (before)
A1: 6 Single holiday - collect before
A2: Simulated holiday on Thu 25 Dec 2025 (1 closed day, no weekend touching it): collected on Wed 24 Dec. Interest unchanged.
A4: Disbursement date (LD_Dis_Date) | B4: 2025-11-03
A5: Amount (LD_Dis_Amt) | B5: 1000000
A6: Rate per month % (LD_IntRate) | B6: 2
A7: Term = installments (LD_Term) | B7: 4
A8: Type (LD_Type) | B8: ថេរ (flat)
A9: Currency | B9: រៀល (KHR)
A10: Unit (LD_Unit) | B10: រោងចក្រ (factory, code 5)
A11: First payment (LD_First_Date) | B11: 2025-11-10
A12: Maturity (LD_Mat_Date) | B12: 2025-12-24
A13: Holidays in range | B13: 2025-11-04 (BK_Holiday), 2025-11-05 (BK_Holiday), 2025-11-06 (BK_Holiday), 2025-11-09 (BK_Holiday)
A14: Interest rule: row 1 = Amount x Rate% / 30 x Days; rows 2+ = basis x Rate% / 2 (basis = Amount for flat, previous SH_Balance_Org for declining). KHR amounts in the _Amt columns are rounded up to the next 100 by ReturnRound; _Org keeps the exact value.
A16: No | B16: Payday (10th/25th) | C16: SH_Date (due date) | D16: Weekday | E16: Shifted? | F16: Days of interest | G16: SH_Prn_Org | H16: SH_Int_Org | I16: SH_Balance_Org | J16: SH_Prn_Amt | K16: SH_Int_Amt | L16: SH_Balance | M16: Total to pay (Prn+Int)
A17: 1 | B17: 2025-11-10 | C17: 2025-11-10 | D17: Monday | F17: 7 | G17: 250000 | H17: 4666.6667 | I17: 750000 | J17: 250000 | K17: 4700 | L17: 750000 | M17: =J17+K17
A18: 2 | B18: 2025-11-25 | C18: 2025-11-25 | D18: Tuesday | F18: 15 | G18: 250000 | H18: 10000 | I18: 500000 | J18: 250000 | K18: 10000 | L18: 500000 | M18: =J18+K18
A19: 3 | B19: 2025-12-10 | C19: 2025-12-10 | D19: Wednesday | F19: 15 | G19: 250000 | H19: 10000 | I19: 250000 | J19: 250000 | K19: 10000 | L19: 250000 | M19: =J19+K19
A20: 4 | B20: 2025-12-25 | C20: 2025-12-24 | D20: Wednesday | E20: yes | F20: 15 | G20: 250000 | H20: 10000 | I20: 0 | J20: 250000 | K20: 10000 | L20: 0 | M20: =J20+K20
A21: Total | G21: =SUM(G17:G20) | H21: =SUM(H17:H20) | J21: =SUM(J17:J20) | K21: =SUM(K17:K20) | M21: =SUM(M17:M20)
A22: Check: principal total equals amount | G22: =IF(ROUND(G21-B5,2)=0,"OK","DIFF")
A23: Legend: yellow = due date moved off a weekend/holiday; green = first installment pro-rated by days.

Sheet 7 Holiday + weekend (after)
A1: 7 Holiday + weekend - collect after
A2: Simulated holiday on Fri 10 Apr 2026 joined to the weekend (3 closed days): collected on Mon 13 Apr. Also 10 Jan / 25 Jan 2026 weekends.
A4: Disbursement date (LD_Dis_Date) | B4: 2025-12-01
A5: Amount (LD_Dis_Amt) | B5: 1000000
A6: Rate per month % (LD_IntRate) | B6: 2
A7: Term = installments (LD_Term) | B7: 10
A8: Type (LD_Type) | B8: ថេរ (flat)
A9: Currency | B9: រៀល (KHR)
A10: Unit (LD_Unit) | B10: រោងចក្រ (factory, code 5)
A11: First payment (LD_First_Date) | B11: 2025-12-10
A12: Maturity (LD_Mat_Date) | B12: 2026-04-27
A13: Holidays in range | B13: 2025-12-29 (BK_Holiday), 2026-04-10 (simulated)
A14: Interest rule: row 1 = Amount x Rate% / 30 x Days; rows 2+ = basis x Rate% / 2 (basis = Amount for flat, previous SH_Balance_Org for declining). KHR amounts in the _Amt columns are rounded up to the next 100 by ReturnRound; _Org keeps the exact value.
A16: No | B16: Payday (10th/25th) | C16: SH_Date (due date) | D16: Weekday | E16: Shifted? | F16: Days of interest | G16: SH_Prn_Org | H16: SH_Int_Org | I16: SH_Balance_Org | J16: SH_Prn_Amt | K16: SH_Int_Amt | L16: SH_Balance | M16: Total to pay (Prn+Int)
A17: 1 | B17: 2025-12-10 | C17: 2025-12-10 | D17: Wednesday | F17: 9 | G17: 100000 | H17: 6000 | I17: 900000 | J17: 100000 | K17: 6000 | L17: 900000 | M17: =J17+K17
A18: 2 | B18: 2025-12-25 | C18: 2025-12-25 | D18: Thursday | F18: 15 | G18: 100000 | H18: 10000 | I18: 800000 | J18: 100000 | K18: 10000 | L18: 800000 | M18: =J18+K18
A19: 3 | B19: 2026-01-10 | C19: 2026-01-12 | D19: Monday | E19: yes | F19: 16 | G19: 100000 | H19: 10000 | I19: 700000 | J19: 100000 | K19: 10000 | L19: 700000 | M19: =J19+K19
A20: 4 | B20: 2026-01-25 | C20: 2026-01-26 | D20: Monday | E20: yes | F20: 15 | G20: 100000 | H20: 10000 | I20: 600000 | J20: 100000 | K20: 10000 | L20: 600000 | M20: =J20+K20
A21: 5 | B21: 2026-02-10 | C21: 2026-02-10 | D21: Tuesday | F21: 16 | G21: 100000 | H21: 10000 | I21: 500000 | J21: 100000 | K21: 10000 | L21: 500000 | M21: =J21+K21
A22: 6 | B22: 2026-02-25 | C22: 2026-02-25 | D22: Wednesday | F22: 15 | G22: 100000 | H22: 10000 | I22: 400000 | J22: 100000 | K22: 10000 | L22: 400000 | M22: =J22+K22
A23: 7 | B23: 2026-03-10 | C23: 2026-03-10 | D23: Tuesday | F23: 13 | G23: 100000 | H23: 10000 | I23: 300000 | J23: 100000 | K23: 10000 | L23: 300000 | M23: =J23+K23
A24: 8 | B24: 2026-03-25 | C24: 2026-03-25 | D24: Wednesday | F24: 15 | G24: 100000 | H24: 10000 | I24: 200000 | J24: 100000 | K24: 10000 | L24: 200000 | M24: =J24+K24
A25: 9 | B25: 2026-04-10 | C25: 2026-04-13 | D25: Monday | E25: yes | F25: 16 | G25: 100000 | H25: 10000 | I25: 100000 | J25: 100000 | K25: 10000 | L25: 100000 | M25: =J25+K25
A26: 10 | B26: 2026-04-25 | C26: 2026-04-27 | D26: Monday | E26: yes | F26: 15 | G26: 100000 | H26: 10000 | I26: 0 | J26: 100000 | K26: 10000 | L26: 0 | M26: =J26+K26
A27: Total | G27: =SUM(G17:G26) | H27: =SUM(H17:H26) | J27: =SUM(J17:J26) | K27: =SUM(K17:K26) | M27: =SUM(M17:M26)
A28: Check: principal total equals amount | G28: =IF(ROUND(G27-B5,2)=0,"OK","DIFF")
A29: Legend: yellow = due date moved off a weekend/holiday; green = first installment pro-rated by days.

Sheet 8 Two holidays in a row (after)
A1: 8 Two holidays in a row - after
A2: Simulated holidays Tue 25 Nov and Wed 26 Nov 2025 (2 closed days): collected Thu 27 Nov.
A4: Disbursement date (LD_Dis_Date) | B4: 2025-11-03
A5: Amount (LD_Dis_Amt) | B5: 1000000
A6: Rate per month % (LD_IntRate) | B6: 2
A7: Term = installments (LD_Term) | B7: 3
A8: Type (LD_Type) | B8: ថេរ (flat)
A9: Currency | B9: រៀល (KHR)
A10: Unit (LD_Unit) | B10: រោងចក្រ (factory, code 5)
A11: First payment (LD_First_Date) | B11: 2025-11-10
A12: Maturity (LD_Mat_Date) | B12: 2025-12-10
A13: Holidays in range | B13: 2025-11-04 (BK_Holiday), 2025-11-05 (BK_Holiday), 2025-11-06 (BK_Holiday), 2025-11-09 (BK_Holiday), 2025-11-25 (simulated), 2025-11-26 (simulated)
A14: Interest rule: row 1 = Amount x Rate% / 30 x Days; rows 2+ = basis x Rate% / 2 (basis = Amount for flat, previous SH_Balance_Org for declining). KHR amounts in the _Amt columns are rounded up to the next 100 by ReturnRound; _Org keeps the exact value.
A16: No | B16: Payday (10th/25th) | C16: SH_Date (due date) | D16: Weekday | E16: Shifted? | F16: Days of interest | G16: SH_Prn_Org | H16: SH_Int_Org | I16: SH_Balance_Org | J16: SH_Prn_Amt | K16: SH_Int_Amt | L16: SH_Balance | M16: Total to pay (Prn+Int)
A17: 1 | B17: 2025-11-10 | C17: 2025-11-10 | D17: Monday | F17: 7 | G17: 333333.33 | H17: 4666.6667 | I17: 666666.67 | J17: 333400 | K17: 4700 | L17: 666700 | M17: =J17+K17
A18: 2 | B18: 2025-11-25 | C18: 2025-11-27 | D18: Thursday | E18: yes | F18: 15 | G18: 333333.33 | H18: 10000 | I18: 333333.34 | J18: 333400 | K18: 10000 | L18: 333400 | M18: =J18+K18
A19: 3 | B19: 2025-12-10 | C19: 2025-12-10 | D19: Wednesday | F19: 15 | G19: 333333.34 | H19: 10000 | I19: 0 | J19: 333400 | K19: 10000 | L19: 0 | M19: =J19+K19
A20: Total | G20: =SUM(G17:G19) | H20: =SUM(H17:H19) | J20: =SUM(J17:J19) | K20: =SUM(K17:K19) | M20: =SUM(M17:M19)
A21: Check: principal total equals amount | G21: =IF(ROUND(G20-B5,2)=0,"OK","DIFF")
A22: Legend: yellow = due date moved off a weekend/holiday; green = first installment pro-rated by days.

Sheet 9 USD loan (no rounding)
A1: 9 USD loan - no rounding
A2: USD 500 at 2.5%/month, 4 installments, declining: amounts are stored as computed, no rounding to 100.
A4: Disbursement date (LD_Dis_Date) | B4: 2025-11-12
A5: Amount (LD_Dis_Amt) | B5: 500
A6: Rate per month % (LD_IntRate) | B6: 2.5
A7: Term = installments (LD_Term) | B7: 4
A8: Type (LD_Type) | B8: ចុះ (declining)
A9: Currency | B9: ដុល្លារ (USD)
A10: Unit (LD_Unit) | B10: រោងចក្រ (factory, code 5)
A11: First payment (LD_First_Date) | B11: 2025-11-25
A12: Maturity (LD_Mat_Date) | B12: 2026-01-12
A13: Holidays in range | B13: 2025-12-29 (BK_Holiday)
A14: Interest rule: row 1 = Amount x Rate% / 30 x Days; rows 2+ = basis x Rate% / 2 (basis = Amount for flat, previous SH_Balance_Org for declining). KHR amounts in the _Amt columns are rounded up to the next 100 by ReturnRound; _Org keeps the exact value.
A16: No | B16: Payday (10th/25th) | C16: SH_Date (due date) | D16: Weekday | E16: Shifted? | F16: Days of interest | G16: SH_Prn_Org | H16: SH_Int_Org | I16: SH_Balance_Org | J16: SH_Prn_Amt | K16: SH_Int_Amt | L16: SH_Balance | M16: Total to pay (Prn+Int)
A17: 1 | B17: 2025-11-25 | C17: 2025-11-25 | D17: Tuesday | F17: 13 | G17: 125 | H17: 5.4166667 | I17: 375 | J17: 125 | K17: 5.4166667 | L17: 375 | M17: =J17+K17
A18: 2 | B18: 2025-12-10 | C18: 2025-12-10 | D18: Wednesday | F18: 15 | G18: 125 | H18: 4.6875 | I18: 250 | J18: 125 | K18: 4.6875 | L18: 250 | M18: =J18+K18
A19: 3 | B19: 2025-12-25 | C19: 2025-12-25 | D19: Thursday | F19: 15 | G19: 125 | H19: 3.125 | I19: 125 | J19: 125 | K19: 3.125 | L19: 125 | M19: =J19+K19
A20: 4 | B20: 2026-01-10 | C20: 2026-01-12 | D20: Monday | E20: yes | F20: 16 | G20: 125 | H20: 1.5625 | I20: 0 | J20: 125 | K20: 1.5625 | L20: 0 | M20: =J20+K20
A21: Total | G21: =SUM(G17:G20) | H21: =SUM(H17:H20) | J21: =SUM(J17:J20) | K21: =SUM(K17:K20) | M21: =SUM(M17:M20)
A22: Check: principal total equals amount | G22: =IF(ROUND(G21-B5,2)=0,"OK","DIFF")
A23: Legend: yellow = due date moved off a weekend/holiday; green = first installment pro-rated by days.

Sheet 10 Principal remainder
A1: 10 Principal remainder
A2: 1,000,000 KHR over 7 installments: 142,857.14 x 6 and the last one 142,857.16 so the balance ends at exactly 0.
A4: Disbursement date (LD_Dis_Date) | B4: 2025-11-03
A5: Amount (LD_Dis_Amt) | B5: 1000000
A6: Rate per month % (LD_IntRate) | B6: 2
A7: Term = installments (LD_Term) | B7: 7
A8: Type (LD_Type) | B8: ថេរ (flat)
A9: Currency | B9: រៀល (KHR)
A10: Unit (LD_Unit) | B10: រោងចក្រ (factory, code 5)
A11: First payment (LD_First_Date) | B11: 2025-11-10
A12: Maturity (LD_Mat_Date) | B12: 2026-02-10
A13: Holidays in range | B13: 2025-11-04 (BK_Holiday), 2025-11-05 (BK_Holiday), 2025-11-06 (BK_Holiday), 2025-11-09 (BK_Holiday), 2025-12-29 (BK_Holiday)
A14: Interest rule: row 1 = Amount x Rate% / 30 x Days; rows 2+ = basis x Rate% / 2 (basis = Amount for flat, previous SH_Balance_Org for declining). KHR amounts in the _Amt columns are rounded up to the next 100 by ReturnRound; _Org keeps the exact value.
A16: No | B16: Payday (10th/25th) | C16: SH_Date (due date) | D16: Weekday | E16: Shifted? | F16: Days of interest | G16: SH_Prn_Org | H16: SH_Int_Org | I16: SH_Balance_Org | J16: SH_Prn_Amt | K16: SH_Int_Amt | L16: SH_Balance | M16: Total to pay (Prn+Int)
A17: 1 | B17: 2025-11-10 | C17: 2025-11-10 | D17: Monday | F17: 7 | G17: 142857.14 | H17: 4666.6667 | I17: 857142.86 | J17: 142900 | K17: 4700 | L17: 857200 | M17: =J17+K17
A18: 2 | B18: 2025-11-25 | C18: 2025-11-25 | D18: Tuesday | F18: 15 | G18: 142857.14 | H18: 10000 | I18: 714285.72 | J18: 142900 | K18: 10000 | L18: 714300 | M18: =J18+K18
A19: 3 | B19: 2025-12-10 | C19: 2025-12-10 | D19: Wednesday | F19: 15 | G19: 142857.14 | H19: 10000 | I19: 571428.58 | J19: 142900 | K19: 10000 | L19: 571500 | M19: =J19+K19
A20: 4 | B20: 2025-12-25 | C20: 2025-12-25 | D20: Thursday | F20: 15 | G20: 142857.14 | H20: 10000 | I20: 428571.44 | J20: 142900 | K20: 10000 | L20: 428600 | M20: =J20+K20
A21: 5 | B21: 2026-01-10 | C21: 2026-01-12 | D21: Monday | E21: yes | F21: 16 | G21: 142857.14 | H21: 10000 | I21: 285714.3 | J21: 142900 | K21: 10000 | L21: 285800 | M21: =J21+K21
A22: 6 | B22: 2026-01-25 | C22: 2026-01-26 | D22: Monday | E22: yes | F22: 15 | G22: 142857.14 | H22: 10000 | I22: 142857.16 | J22: 142900 | K22: 10000 | L22: 142900 | M22: =J22+K22
A23: 7 | B23: 2026-02-10 | C23: 2026-02-10 | D23: Tuesday | F23: 16 | G23: 142857.16 | H23: 10000 | I23: 0 | J23: 142900 | K23: 10000 | L23: 0 | M23: =J23+K23
A24: Total | G24: =SUM(G17:G23) | H24: =SUM(H17:H23) | J24: =SUM(J17:J23) | K24: =SUM(K17:K23) | M24: =SUM(M17:M23)
A25: Check: principal total equals amount | G25: =IF(ROUND(G24-B5,2)=0,"OK","DIFF")
A26: Legend: yellow = due date moved off a weekend/holiday; green = first installment pro-rated by days.

Sheet 11 Year end rollover
A1: 11 Year end rollover
A2: Disbursed 20 Dec 2025: 25 Dec kept (5 days), then 10 Jan 2026 (Sat -> Mon 12), 25 Jan (Sun -> Mon 26). DB holiday 29 Dec is not a payday so it has no effect.
A4: Disbursement date (LD_Dis_Date) | B4: 2025-12-20
A5: Amount (LD_Dis_Amt) | B5: 3000000
A6: Rate per month % (LD_IntRate) | B6: 2
A7: Term = installments (LD_Term) | B7: 4
A8: Type (LD_Type) | B8: ចុះ (declining)
A9: Currency | B9: រៀល (KHR)
A10: Unit (LD_Unit) | B10: រោងចក្រ (factory, code 5)
A11: First payment (LD_First_Date) | B11: 2025-12-25
A12: Maturity (LD_Mat_Date) | B12: 2026-02-10
A13: Holidays in range | B13: 2025-12-29 (BK_Holiday)
A14: Interest rule: row 1 = Amount x Rate% / 30 x Days; rows 2+ = basis x Rate% / 2 (basis = Amount for flat, previous SH_Balance_Org for declining). KHR amounts in the _Amt columns are rounded up to the next 100 by ReturnRound; _Org keeps the exact value.
A16: No | B16: Payday (10th/25th) | C16: SH_Date (due date) | D16: Weekday | E16: Shifted? | F16: Days of interest | G16: SH_Prn_Org | H16: SH_Int_Org | I16: SH_Balance_Org | J16: SH_Prn_Amt | K16: SH_Int_Amt | L16: SH_Balance | M16: Total to pay (Prn+Int)
A17: 1 | B17: 2025-12-25 | C17: 2025-12-25 | D17: Thursday | F17: 5 | G17: 750000 | H17: 10000 | I17: 2250000 | J17: 750000 | K17: 10000 | L17: 2250000 | M17: =J17+K17
A18: 2 | B18: 2026-01-10 | C18: 2026-01-12 | D18: Monday | E18: yes | F18: 16 | G18: 750000 | H18: 22500 | I18: 1500000 | J18: 750000 | K18: 22500 | L18: 1500000 | M18: =J18+K18
A19: 3 | B19: 2026-01-25 | C19: 2026-01-26 | D19: Monday | E19: yes | F19: 15 | G19: 750000 | H19: 15000 | I19: 750000 | J19: 750000 | K19: 15000 | L19: 750000 | M19: =J19+K19
A20: 4 | B20: 2026-02-10 | C20: 2026-02-10 | D20: Tuesday | F20: 16 | G20: 750000 | H20: 7500 | I20: 0 | J20: 750000 | K20: 7500 | L20: 0 | M20: =J20+K20
A21: Total | G21: =SUM(G17:G20) | H21: =SUM(H17:H20) | J21: =SUM(J17:J20) | K21: =SUM(K17:K20) | M21: =SUM(M17:M20)
A22: Check: principal total equals amount | G22: =IF(ROUND(G21-B5,2)=0,"OK","DIFF")
A23: Legend: yellow = due date moved off a weekend/holiday; green = first installment pro-rated by days.
